{
 "charts": [],
 "content": "[{\"type\":\"header\",\"data\":{\"text\":\"<span class=\\\"h4\\\">Junta de agua potable de Jerusal\u00e9n</span>\",\"col\":12}},{\"type\":\"header\",\"data\":{\"text\":\"<span class=\\\"h4\\\"><b>Configuraciones</b></span>\",\"col\":12}},{\"type\":\"shortcut\",\"data\":{\"shortcut_name\":\"Lista de tarifas\",\"col\":3}},{\"type\":\"shortcut\",\"data\":{\"shortcut_name\":\"Lista de barrios\",\"col\":3}},{\"type\":\"header\",\"data\":{\"text\":\"<span class=\\\"h4\\\"><b>Medidores y clientes</b></span>\",\"col\":12}},{\"type\":\"shortcut\",\"data\":{\"shortcut_name\":\"Lista de clientes\",\"col\":3}},{\"type\":\"shortcut\",\"data\":{\"shortcut_name\":\"Lista de medidores\",\"col\":3}},{\"type\":\"header\",\"data\":{\"text\":\"<span class=\\\"h4\\\"><b>Planillas y pagos</b></span>\",\"col\":12}},{\"type\":\"shortcut\",\"data\":{\"shortcut_name\":\"Periodos de pago\",\"col\":3}},{\"type\":\"shortcut\",\"data\":{\"shortcut_name\":\"Mediciones\",\"col\":3}},{\"type\":\"shortcut\",\"data\":{\"shortcut_name\":\"Lista de pagos\",\"col\":3}},{\"type\":\"shortcut\",\"data\":{\"shortcut_name\":\"Planillas de agua\",\"col\":3}},{\"type\":\"shortcut\",\"data\":{\"shortcut_name\":\"Lista de mingas\",\"col\":3}}]",
 "creation": "2022-12-26 16:02:03.099633",
 "docstatus": 0,
 "doctype": "Workspace",
 "for_user": "",
 "hide_custom": 0,
 "icon": "heart-active",
 "idx": 0,
 "label": "Junta agua",
 "links": [],
 "modified": "2023-01-02 00:03:41.783121",
 "modified_by": "Administrator",
 "module": "Junta de Agua Potable Jerusalen",
 "name": "Junta agua",
 "owner": "Administrator",
 "parent_page": "",
 "public": 1,
 "quick_lists": [],
 "roles": [],
 "sequence_id": 31.0,
 "shortcuts": [
  {
   "color": "Yellow",
   "doc_view": "List",
   "label": "Periodos de pago",
   "link_to": "Periodo Pago",
   "type": "DocType"
  },
  {
   "color": "Grey",
   "doc_view": "List",
   "label": "Lista de pagos",
   "link_to": "Pago Agua",
   "type": "DocType"
  },
  {
   "color": "Grey",
   "doc_view": "List",
   "label": "Lista de mingas",
   "link_to": "Minga",
   "type": "DocType"
  },
  {
   "color": "Grey",
   "doc_view": "List",
   "label": "Lista de tarifas",
   "link_to": "Tarifa",
   "type": "DocType"
  },
  {
   "color": "Grey",
   "doc_view": "List",
   "label": "Lista de barrios",
   "link_to": "Barrio",
   "type": "DocType"
  },
  {
   "color": "Grey",
   "doc_view": "List",
   "label": "Mediciones",
   "link_to": "Medicion",
   "type": "DocType"
  },
  {
   "color": "Green",
   "doc_view": "List",
   "label": "Lista de clientes",
   "link_to": "Customer",
   "type": "DocType"
  },
  {
   "color": "Blue",
   "doc_view": "List",
   "label": "Lista de medidores",
   "link_to": "Medidor",
   "type": "DocType"
  },
  {
   "color": "Grey",
   "doc_view": "List",
   "label": "Planillas de agua",
   "link_to": "Planilla",
   "type": "DocType"
  }
 ],
 "title": "Junta agua"
}